[
	{"case": 11, "type": "lane_departure_opposite", "parameters": {"max_speed": 0.0, "relative sp": 0.0, "dis": 40, "ratio": 1}},
 	{"case": 15, "type": "lane_departure_same", "parameters": {"max_speed": 0.0, "relative sp": 2, "dis": 5, "ratio": 0.7}},
 	{"case": 16, "type": "cut_in", "parameters": {"max_speed": 0.0, "relative sp": 2, "dis": 10, "ratio": 1}},
 	{"case": 19, "type": "left_turn_turn", "parameters": {"max_speed": 0.0, "dis": 5, "sp": 15.555555555555555}},
 	{"case": 28, "type": "vehicle_encroachment", "parameters": {"max_speed": 0.0, "dis": 5, "angle": 90}},
 	{"case": 30, "type": "car_following", "parameters": {"max_speed": 0.0, "sp": 12.075, "acc": 3, "dec": -4}},
 	{"case": 31, "type": "right_turn_turn", "parameters": {"max_speed": 0.0, "dis": 5, "sp": 20.0}},
 	{"case": 42, "type": "vehicle_encroachment", "parameters": {"max_speed": 0.0, "dis": 5, "angle": 90}},
 	{"case": 45, "type": "car_following", "parameters": {"max_speed": 0.0, "sp": 22.808333333333334, "acc": 3, "dec": -4}},
 	{"case": 49, "type": "left_turn_turn", "parameters": {"max_speed": 0.0, "dis": 5, "sp": 20.0}},
 	{"case": 57, "type": "lane_departure_opposite", "parameters": {"max_speed": 0.0, "relative sp": 0.0, "dis": 40, "ratio": 1}},
 	{"case": 58, "type": "left_turn_turn", "parameters": {"max_speed": 0.0, "dis": 5, "sp": 20.0}},
 	{"case": 63, "type": "lane_departure_same", "parameters": {"max_speed": 0.0, "relative sp": 2, "dis": 5, "ratio": 0.7}},
 	{"case": 66, "type": "lane_departure_opposite", "parameters": {"max_speed": 0.0, "relative sp": 0.0, "dis": 40, "ratio": 1}},
 	{"case": 68, "type": "traffic_signal", "parameters": {"max_speed": 0.0}},
 	{"case": 69, "type": "left_turn_turn", "parameters": {"max_speed": 0.0, "dis": 5, "sp": 20.0}},
 	{"case": 76, "type": "lane_departure_opposite", "parameters": {"max_speed": 0.0, "relative sp": 0.0, "dis": 40, "ratio": 1}},
 	{"case": 89, "type": "traffic_signal", "parameters": {"max_speed": 0.0}},
 	{"case": 95, "type": "left_turn_turn", "parameters": {"max_speed": 0.0, "dis": 5, "sp": 20.0}},
 	{"case": 98, "type": "left_turn_turn", "parameters": {"max_speed": 0.0, "dis": 5, "sp": 24.72222222222222}},
 	{"case": 102, "type": "left_turn_turn", "parameters": {"max_speed": 0.0, "dis": 5, "sp": 24.72222222222222}},
 	{"case": 104, "type": "right_turn_turn", "parameters": {"max_speed": 0.0, "dis": 5, "sp": 15.555555555555555}},
 	{"case": 132, "type": "lane_departure_opposite", "parameters": {"max_speed": 0.0, "relative sp": 0.0, "dis": 40, "ratio": 1}},
 	{"case": 136, "type": "left_turn_turn", "parameters": {"max_speed": 0.0, "dis": 5, "sp": 11.11111111111111}},
 	{"case": 138, "type": "left_turn_turn", "parameters": {"max_speed": 0.0, "dis": 5, "sp": 11.11111111111111}},
 	{"case": 139, "type": "right_turn_turn", "parameters": {"max_speed": 0.0, "dis": 5, "sp": 13.333333333333332}},
 	{"case": 150, "type": "vehicle_encroachment", "parameters": {"max_speed": 0.0, "dis": 5, "angle": 90}},
 	{"case": 162, "type": "lane_departure_opposite", "parameters": {"max_speed": 0.0, "relative sp": 0.0, "dis": 40, "ratio": 1}},
 	{"case": 164, "type": "left_turn_turn", "parameters": {"max_speed": 0.0, "dis": 5, "sp": 15.555555555555555}},
 	{"case": 180, "type": "left_turn_turn", "parameters": {"max_speed": 0.0, "dis": 5, "sp": 24.72222222222222}},
 	{"case": 193, "type": "left_turn_turn", "parameters": {"max_speed": 0.0, "dis": 5, "sp": 17.77777777777778}},
 	{"case": 197, "type": "lane_departure_opposite", "parameters": {"max_speed": 0.0, "relative sp": 0.0, "dis": 40, "ratio": 1}},
 	{"case": 220, "type": "vehicle_encroachment", "parameters": {"max_speed": 0.0, "dis": 5, "angle": 90}},
 	{"case": 227, "type": "right_turn_turn", "parameters": {"max_speed": 0.0, "dis": 5, "sp": 26.944444444444443}},
 	{"case": 230, "type": "left_turn_turn", "parameters": {"max_speed": 0.0, "dis": 5, "sp": 20.0}},
 	{"case": 231, "type": "left_turn_turn", "parameters": {"max_speed": 0.0, "dis": 5, "sp": 15.555555555555555}},
 	{"case": 244, "type": "vehicle_encroachment", "parameters": {"max_speed": 0.0, "dis": 5, "angle": 90}},
 	{"case": 248, "type": "left_turn_turn", "parameters": {"max_speed": 0.0, "dis": 5, "sp": 17.77777777777778}},
 	{"case": 253, "type": "left_turn_turn", "parameters": {"max_speed": 0.0, "dis": 5, "sp": 11.11111111111111}},
 	{"case": 266, "type": "left_turn_turn", "parameters": {"max_speed": 0.0, "dis": 5, "sp": 15.555555555555555}},
 	{"case": 267, "type": "car_following", "parameters": {"max_speed": 0.0, "sp": 25.268055555555556, "acc": 3, "dec": -4}},
 	{"case": 291, "type": "left_turn_turn", "parameters": {"max_speed": 0.0, "dis": 5, "sp": 20.0}},
 	{"case": 299, "type": "vehicle_encroachment", "parameters": {"max_speed": 0.0, "dis": 5, "angle": 90}},
 	{"case": 303, "type": "lane_departure_opposite", "parameters": {"max_speed": 0.0, "relative sp": 0.0, "dis": 40, "ratio": 1}},
 	{"case": 310, "type": "car_following", "parameters": {"max_speed": 0.0, "sp": 16.944444444444443, "acc": 3, "dec": -4}},
 	{"case": 311, "type": "left_turn_turn", "parameters": {"max_speed": 0.0, "dis": 5, "sp": 11.11111111111111}},
 	{"case": 324, "type": "left_turn_turn", "parameters": {"max_speed": 0.0, "dis": 5, "sp": 17.77777777777778}},
 	{"case": 341, "type": "lane_departure_opposite", "parameters": {"max_speed": 0.0, "relative sp": 0.0, "dis": 40, "ratio": 1}},
 	{"case": 350, "type": "car_following", "parameters": {"max_speed": 0.0, "sp": 28.88888888888889, "acc": 3, "dec": -4}},
 	{"case": 359, "type": "vehicle_encroachment", "parameters": {"max_speed": 0.0, "dis": 5, "angle": 90}},
 	{"case": 363, "type": "left_turn_turn", "parameters": {"max_speed": 0.0, "dis": 5, "sp": 277.5}},
 	{"case": 406, "type": "left_turn_turn", "parameters": {"max_speed": 0.0, "dis": 5, "sp": 20.0}},
 	{"case": 408, "type": "left_turn_turn", "parameters": {"max_speed": 0.0, "dis": 5, "sp": 20.0}},
 	{"case": 417, "type": "left_turn_turn", "parameters": {"max_speed": 0.0, "dis": 5, "sp": 20.0}},
 	{"case": 420, "type": "left_turn_turn", "parameters": {"max_speed": 0.0, "dis": 5, "sp": 20.0}},
 	{"case": 426, "type": "lane_departure_opposite", "parameters": {"max_speed": 0.0, "relative sp": 0.0, "dis": 40, "ratio": 1}},
 	{"case": 432, "type": "left_turn_turn", "parameters": {"max_speed": 0.0, "dis": 5, "sp": 17.77777777777778}},
 	{"case": 490, "type": "car_following", "parameters": {"max_speed": 0.0, "sp": 16.904999999999998, "acc": 3, "dec": -4}},
 	{"case": 497, "type": "left_turn_turn", "parameters": {"max_speed": 0.0, "dis": 5, "sp": 11.11111111111111}},
 	{"case": 518, "type": "left_turn_turn", "parameters": {"max_speed": 0.0, "dis": 5, "sp": 11.11111111111111}},
 	{"case": 533, "type": "left_turn_turn", "parameters": {"max_speed": 0.0, "dis": 5, "sp": 26.944444444444443}},
 	{"case": 555, "type": "car_following", "parameters": {"max_speed": 0.0, "sp": 25.0, "acc": 3, "dec": -4}},
 	{"case": 559, "type": "lane_departure_opposite", "parameters": {"max_speed": 0.0, "relative sp": 0.0, "dis": 40, "ratio": 1}},
 	{"case": 567, "type": "left_turn_turn", "parameters": {"max_speed": 0.0, "dis": 5, "sp": 15.555555555555555}},
 	{"case": 580, "type": "left_turn_turn", "parameters": {"max_speed": 0.0, "dis": 5, "sp": 24.72222222222222}},
 	{"case": 594, "type": "left_turn_turn", "parameters": {"max_speed": 0.0, "dis": 5, "sp": 22.22222222222222}},
 	{"case": 597, "type": "vehicle_encroachment", "parameters": {"max_speed": 0.0, "dis": 5, "angle": 90}},
 	{"case": 623, "type": "lane_departure_opposite", "parameters": {"max_speed": 0.0, "relative sp": 0.0, "dis": 40, "ratio": 1}},
 	{"case": 665, "type": "left_turn_turn", "parameters": {"max_speed": 0.0, "dis": 5, "sp": 20.0}},
 	{"case": 687, "type": "left_turn_turn", "parameters": {"max_speed": 0.0, "dis": 5, "sp": 20.0}},
 	{"case": 702, "type": "vehicle_encroachment", "parameters": {"max_speed": 0.0, "dis": 5, "angle": 90}},
 	{"case": 709, "type": "car_following", "parameters": {"max_speed": 0.0, "sp": 13.90861111111111, "acc": 3, "dec": -4}},
 	{"case": 718, "type": "car_following", "parameters": {"max_speed": 0.0, "sp": 18.067777777777778, "acc": 3, "dec": -4}},
 	{"case": 725, "type": "vehicle_encroachment", "parameters": {"max_speed": 0.0, "dis": 5, "angle": 90}},
 	{"case": 730, "type": "lane_departure_opposite", "parameters": {"max_speed": 0.0, "relative sp": 0.0, "dis": 40, "ratio": 1}},
 	{"case": 731, "type": "lane_departure_opposite", "parameters": {"max_speed": 0.0, "relative sp": 0.0, "dis": 40, "ratio": 1}},
 	{"case": 732, "type": "car_following", "parameters": {"max_speed": 0.0, "sp": 16.994444444444444, "acc": 3, "dec": -4}},
 	{"case": 733, "type": "left_turn_turn", "parameters": {"max_speed": 0.0, "dis": 5, "sp": 20.0}},
 	{"case": 742, "type": "right_turn_turn", "parameters": {"max_speed": 0.0, "dis": 5, "sp": 29.166666666666664}},
 	{"case": 748, "type": "lane_departure_opposite", "parameters": {"max_speed": 0.0, "relative sp": 0.0, "dis": 40, "ratio": 1}},
 	{"case": 800, "type": "left_turn_turn", "parameters": {"max_speed": 0.0, "dis": 5, "sp": 17.77777777777778}},
 	{"case": 806, "type": "car_following", "parameters": {"max_speed": 0.0, "sp": 4.025, "acc": 3, "dec": -4}},
 	{"case": 814, "type": "vehicle_encroachment", "parameters": {"max_speed": 0.0, "dis": 5, "angle": 90}},
 	{"case": 826, "type": "left_turn_turn", "parameters": {"max_speed": 0.0, "dis": 5, "sp": 24.72222222222222}},
 	{"case": 854, "type": "vehicle_encroachment", "parameters": {"max_speed": 0.0, "dis": 5, "angle": 90}},
 	{"case": 898, "type": "left_turn_turn", "parameters": {"max_speed": 0.0, "dis": 5, "sp": 20.0}},
 	{"case": 915, "type": "left_turn_turn", "parameters": {"max_speed": 0.0, "dis": 5, "sp": 15.555555555555555}},
 	{"case": 916, "type": "left_turn_turn", "parameters": {"max_speed": 0.0, "dis": 5, "sp": 11.11111111111111}},
 	{"case": 972, "type": "vehicle_encroachment", "parameters": {"max_speed": 0.0, "dis": 5, "angle": 90}},
 	{"case": 982, "type": "left_turn_turn", "parameters": {"max_speed": 0.0, "dis": 5, "sp": 24.72222222222222}},
 	{"case": 990, "type": "vehicle_encroachment", "parameters": {"max_speed": 0.0, "dis": 5, "angle": 90}},
 	{"case": 1034, "type": "left_turn_turn", "parameters": {"max_speed": 0.0, "dis": 5, "sp": 24.72222222222222}},
 	{"case": 1070, "type": "car_following", "parameters": {"max_speed": 0.0, "sp": 3.888888888888889, "acc": 3, "dec": -4}},
 	{"case": 1089, "type": "left_turn_turn", "parameters": {"max_speed": 0.0, "dis": 5, "sp": 20.0}},
 	{"case": 1094, "type": "car_following", "parameters": {"max_speed": 0.0, "sp": 21.666666666666668, "acc": 3, "dec": -4}},
 	{"case": 1098, "type": "left_turn_turn", "parameters": {"max_speed": 0.0, "dis": 5, "sp": 17.77777777777778}},
 	{"case": 1125, "type": "left_turn_turn", "parameters": {"max_speed": 0.0, "dis": 5, "sp": 20.0}},
 	{"case": 1149, "type": "lane_departure_opposite", "parameters": {"max_speed": 0.0, "relative sp": 0.0, "dis": 40, "ratio": 1}},
 	{"case": 1157, "type": "right_turn_turn", "parameters": {"max_speed": 0.0, "dis": 5, "sp": 20.0}},
 	{"case": 1216, "type": "left_turn_turn", "parameters": {"max_speed": 0.0, "dis": 5, "sp": 24.72222222222222}},
 	{"case": 980035, "type": "vehicle_encroachment", "parameters": {"max_speed": 0.0, "dis": 5, "angle": 90}},
 	{"case": 980038, "type": "car_following", "parameters": {"max_speed": 0.0, "sp": 2.5, "acc": 3, "dec": -4}},
 	{"case": 980039, "type": "vehicle_encroachment", "parameters": {"max_speed": 0.0, "dis": 5, "angle": 90}},
 	{"case": 980054, "type": "left_turn_turn", "parameters": {"max_speed": 0.0, "dis": 5, "sp": 15.555555555555555}},
 	{"case": 980112, "type": "right_turn_turn", "parameters": {"max_speed": 0.0, "dis": 5, "sp": 24.72222222222222}},
 	{"case": 980119, "type": "left_turn_turn", "parameters": {"max_speed": 0.0, "dis": 5, "sp": 20.0}},
 	{"case": 980188, "type": "vehicle_encroachment", "parameters": {"max_speed": 0.0, "dis": 5, "angle": 90}}

]